daily/__init__.py
daily/__main__.py
daily/cli.py
daily/config.py
daily/journal.py
daily/utils.py
daily_diary-0.1.1.dist-info/LICENSE
daily_diary-0.1.1.dist-info/METADATA
daily_diary-0.1.1.dist-info/WHEEL
daily_diary-0.1.1.dist-info/entry_points.txt
daily_diary-0.1.1.dist-info/top_level.txt
daily_diary-0.1.1.dist-info/RECORD
