Metadata-Version: 2.1
Name: daily-diary
Version: 0.1.1
Summary: A command line tool for keeping a markdown diary
Author: Connor Murphy
License: GNU GENERAL PUBLIC LICENSE
Project-URL: Repository, https://github.com/contrick64/daily-diary
Keywords: cli,markdown,journal,diary
Classifier: License :: OSI Approved :: GNU General Public License v3 (GPLv3)
License-File: LICENSE
